{
  "required": true,
  "minVersion": "0.8",
  "package": "sircow.preservedinferno.mixin",
  "refmap": "${mod_id}.refmap.json",
  "compatibilityLevel": "JAVA_18",
  "mixins": [
    "AbstractArrowMixin",
    "AbstractFishMixin",
    "AbstractFurnaceBlockEntityAccessor",
    "AbstractFurnaceBlockEntityMixin",
    "AbstractSkeletonMixin",
    "AbstractThrownPotionMixin",
    "AnvilMenuMixin",
    "ArmorMaterialMixin",
    "AttributesMixin",
    "AxeItemMixin",
    "BlazeMixin",
    "BlocksMixin",
    "BoggedMixin",
    "BrewingStandBlockEntityMixin",
    "CamelMixin",
    "CarversMixin",
    "ChickenMixin",
    "CombatRulesMixin",
    "ConduitBlockEntityMixin",
    "ConsumablesMixin",
    "CrossbowMixin",
    "DrownedMixin",
    "ElderGuardianMixin",
    "EnderDragonMixin",
    "EndermanMixin",
    "EvokerMixin",
    "FishingHookMixin",
    "FishingRodItemMixin",
    "FletchingTableBlockMixin",
    "FoodDataMixin",
    "FoodsMixin",
    "GhastMixin",
    "GiantMixin",
    "GuardianMixin",
    "HoneycombItemMixin",
    "ItemCombinerMenuAccessor",
    "ItemMixin",
    "ItemsMixin",
    "ItemStackMixin",
    "LightningBoltMixin",
    "LiquidBlockMixin",
    "LivingEntityMixin",
    "MaceItemMixin",
    "MagmaCubeMixin",
    "PhantomMixin",
    "PiglinMixin",
    "PlayerMixin",
    "PotionBrewingMixin",
    "PotionsMixin",
    "RabbitMixin",
    "ServerPlayerMixin",
    "SheepMixin",
    "ShovelItemMixin",
    "ShulkerMixin",
    "SkeletonHorseMixin",
    "SmithingMenuMixin",
    "SnifferMixin",
    "SnowGolemMixin",
    "ThrownTridentMixin",
    "ToolMaterialMixin",
    "TridentItemMixin",
    "TurtleMixin",
    "VexMixin",
    "VindicatorMixin",
    "WardenMixin",
    "WitherBossMixin",
    "WitherSkeletonMixin",
    "WolfMixin",
    "ZoglinMixin",
    "ZombieHorseMixin",
    "ZombieMixin",
    "ZombifiedPiglinMixin"
  ],
  "client": [
    "BrewingStandScreenMixin",
    "EntityRenderDispatcherMixin",
    "GuiMixin",
    "ItemInHandRendererMixin"
  ],
  "server": [],
  "injectors": {
    "defaultRequire": 1
  }
}

